pyrtk/__init__.py
pyrtk/main.py
pyrtk/cli/__init__.py
pyrtk/cli/create.py
pyrtk/cli/generate.py
pyrtk/cli/run.py
pyrtk/internal/__init__.py
pyrtk/internal/run_logic.py
pyrtk/scaffold/__init__.py
pyrtk/scaffold/api.py
pyrtk/scaffold/install.py
pyrtk/scaffold/ms.py
tests/__init__.py
tests/test_create.py
pyrtk_cli-0.1.3.dist-info/METADATA
pyrtk_cli-0.1.3.dist-info/WHEEL
pyrtk_cli-0.1.3.dist-info/entry_points.txt
pyrtk_cli-0.1.3.dist-info/top_level.txt
pyrtk_cli-0.1.3.dist-info/RECORD
