Metadata-Version: 2.4
Name: pyrtk-cli
Version: 0.1.3
Summary: A modern CLI for scaffolding and managing FastAPI projects with clean architecture.
Author: Andres Mardones
Classifier: Programming Language :: Python :: 3
Classifier: Operating System :: OS Independent
Classifier: Development Status :: 4 - Beta
Classifier: Intended Audience :: Developers
Classifier: Topic :: Software Development :: Build Tools
Classifier: Framework :: FastAPI
Requires-Python: >=3.7
Requires-Dist: typer>=0.9.0
Requires-Dist: rich>=13.0.0
Requires-Dist: fastapi
Requires-Dist: uvicorn
Requires-Dist: python-dotenv
Dynamic: author
Dynamic: classifier
Dynamic: description
Dynamic: description-content-type
Dynamic: requires-dist
Dynamic: requires-python
Dynamic: summary
